imcar/__init__.py
imcar/__main__.py
imcar/device_view.py
imcar/workers.py
imcar/app/__init__.py
imcar/app/start.py
imcar/gui/AddDevice.md
imcar/gui/CalibrationWidget.py
imcar/gui/ColorbarWidget.py
imcar/gui/ErrorLineItem.py
imcar/gui/MCA_simple_UI.ui
imcar/gui/RegionIndicatorWidget.py
imcar/gui/__init__.py
imcar/gui/calibration_editor.ui
imcar/gui/custom_axes.py
imcar/gui/device_config.py
imcar/gui/helper.py
imcar/gui/icon.ico
imcar/gui/icon.png
imcar/gui/mainwindow.py
imcar/gui/shell.py
imcar/gui/shell_POST.html
imcar/gui/snapshot_evolution.ui
imcar/gui/snapshot_evolution_widget.py
imcar/gui/snapshot_info.ui
imcar/gui/snapshot_save_dialog.py
imcar/gui/snapshot_view.ui
imcar/gui/snapshot_view_widget.py
imcar/gui/test.py
imcar-1.0.8.dist-info/licenses/LICENSE
mca_api/__init__.py
mca_api/data.py
mca_api/device.py
mca_api/device_list.py
mca_api/fitting.py
mca_api/properties.py
mca_api/record_info.py
mca_api/utils.py
mca_api/drivers/__init__.py
mca_api/drivers/caen_n957.py
mca_api/drivers/software_devices.py
imcar-1.0.8.dist-info/METADATA
imcar-1.0.8.dist-info/WHEEL
imcar-1.0.8.dist-info/entry_points.txt
imcar-1.0.8.dist-info/top_level.txt
imcar-1.0.8.dist-info/RECORD
