Metadata-Version: 2.4
Name: imcar
Version: 1.0.8
Author: 2xB
Author-email: 2xB.coding@uni-muenster.de
License-File: LICENSE
Requires-Dist: numpy
Requires-Dist: matplotlib
Requires-Dist: scipy
Requires-Dist: uncertainties
Requires-Dist: pyusb
Requires-Dist: PyQt5
Requires-Dist: pyqtgraph>=0.13.1
Requires-Dist: markdown2
Requires-Dist: faultguard>=1.1.1
Dynamic: author
Dynamic: author-email
Dynamic: description
Dynamic: description-content-type
Dynamic: license-file
Dynamic: requires-dist
